django_svgselect/apps.py
django_svgselect/forms.py
django_svgselect/tests.py
django_svgselect/__init__.py
django_svgselect/static/django_svgselect.js
django_svgselect-0.9.1.dist-info/DESCRIPTION.rst
django_svgselect-0.9.1.dist-info/METADATA
django_svgselect-0.9.1.dist-info/metadata.json
django_svgselect-0.9.1.dist-info/RECORD
django_svgselect-0.9.1.dist-info/top_level.txt
django_svgselect-0.9.1.dist-info/WHEEL
