Metadata-Version: 2.0
Name: django-svgselect
Version: 0.9.1
Summary: A Django form widget that uses SVG files in place of Select widgets.
Home-page: https://github.com/jmickela/django_svgselect
Author: Jason Mickela
Author-email: jason@rootid.in
License: MIT
Keywords: django form widget svg
Platform: UNKNOWN
Classifier: Development Status :: 4 - Beta
Classifier: Intended Audience :: Developers
Classifier: Topic :: Software Development :: Build Tools
Classifier: License :: OSI Approved :: MIT License
Classifier: Programming Language :: Python :: 2
Classifier: Programming Language :: Python :: 2.6
Classifier: Programming Language :: Python :: 2.7
Classifier: Programming Language :: Python :: 3
Classifier: Programming Language :: Python :: 3.3
Classifier: Programming Language :: Python :: 3.4
Classifier: Programming Language :: Python :: 3.5
